{
	"set": "TRV",
	"setName": "東京リベンジャーズ",
	"side": "S",
	"release": "92",
	"id": "070",
	"name": "",
	"jpName": "踏み絵 場地",
	"cardType": "CH",
	"colour": "RED",
	"level": "2",
	"cost": "2",
	"power": "7000",
	"soul": "2",
	"rarity": "C",
	"breakDeckbuilding": false,
	"EN_Equivalent": false,
	"flavourText": "",
	"trigger": [
		"SOUL"
	],
	"ability": [
		"【自】［手札を1枚控え室に置く］ 相手のターン中、バトル中のこのカードが【リバース】した時、あなたはコストを払ってよい。そうしたら、このカードを【レスト】し、次のあなたのアンコールステップの始めに、このカードを控え室に置く。",
		"【自】 共鳴 ［手札の「不良の時代 マイキー」を1枚公開する］ あなたのクライマックスフェイズの始めに、あなたはコストを払ってよい。そうしたら、そのターン中、このカードのパワーを＋6000。"
	],
	"specialAttrib": [
		"リベンジ"
	],
	"version": "3",
	"cardcode": "TRV/S92-070",
	"imageURL": "/wordpress/wp-content/images/cardlist/t/trv_s92/trv_s92_070.png",
	"tags": null
}