{
	"set": "UMA",
	"setName": "アニメ『ウマ娘 シンデレラグレイ』",
	"side": "W",
	"release": "134",
	"id": "023",
	"name": "",
	"jpName": "“憧れの学園生活”ベルノライト",
	"cardType": "CH",
	"colour": "YELLOW",
	"level": "1",
	"cost": "1",
	"power": "1000",
	"soul": "1",
	"rarity": "C",
	"breakDeckbuilding": false,
	"EN_Equivalent": false,
	"flavourText": "",
	"trigger": [
		"SOUL"
	],
	"ability": [
		"【自】 あなたがこのカードの『助太刀』を使った時、あなたのキャラすべてが《ウマ娘》なら、あなたは自分の控え室のレベル1以下のキャラを1枚選び、ストック置場の下に置いてよい。",
		"【起】【カウンター】 助太刀2000 レベル1 ［(1) 手札のこのカードを控え室に置く］ （あなたは自分のフロントアタックされているキャラを1枚選び、そのターン中、パワーを＋2000）"
	],
	"specialAttrib": [
		"ウマ娘",
		"シンデレラグレイ"
	],
	"version": "3",
	"cardcode": "UMA/W134-023",
	"imageURL": "/wordpress/wp-content/images/cardlist/u/uma_w134/uma_w134_023.png",
	"tags": null
}