{
	"set": "P5",
	"setName": "ペルソナ５",
	"side": "S",
	"release": "45",
	"id": "031S",
	"name": "",
	"jpName": "新島 真",
	"cardType": "CH",
	"colour": "GREEN",
	"level": "1",
	"cost": "0",
	"power": "6500",
	"soul": "1",
	"rarity": "SR",
	"breakDeckbuilding": false,
	"EN_Equivalent": false,
	"flavourText": "私は…お姉ちゃんみたいにはなれない。\u003cbr\u003eいつか、分かりあえない時がくる…そんな気がしてた",
	"trigger": null,
	"ability": [
		"【永】 このカードの正面のキャラのレベルがこのカードのレベルより高いなら、このカードはフロントアタックできない。"
	],
	"specialAttrib": [
		"怪盗",
		"生徒会"
	],
	"version": "4",
	"cardcode": "P5/S45-031S",
	"imageURL": "https://ws-tcg.com/wordpress/wp-content/images/p/p5_s45/p5_s45_031s.png",
	"tags": null,
	"expansionId": 180
}