{
	"set": "FT",
	"setName": "FAIRY TAIL 100年クエスト",
	"side": "S",
	"release": "120",
	"id": "081S",
	"name": "",
	"jpName": "神の名を冠する竜の脅威 ウェンディ",
	"cardType": "CH",
	"colour": "BLUE",
	"level": "3",
	"cost": "2",
	"power": "10000",
	"soul": "2",
	"rarity": "SR",
	"breakDeckbuilding": false,
	"EN_Equivalent": false,
	"flavourText": "",
	"trigger": [
		"SOUL"
	],
	"ability": [
		"【自】［手札を1枚控え室に置く］ このカードが手札から舞台に置かれた時、あなたはコストを払ってよい。そうしたら、あなたは自分のクロックの上から1枚を、ストック置場に置く。",
		"【自】【CXコンボ】［(1) 手札を1枚控え室に置く］ あなたのCX置場に「いい加減にしてください!!!」が置かれた時、前列にこのカードがいて、他のあなたの《魔法》のキャラが2枚以上なら、あなたはコストを払ってよい。そうしたら、他のあなたのキャラすべてに、そのターン中、次の能力を与える。『【自】 このカードがアタックした時、あなたは相手の山札の上から1枚を、控え室に置く。そのカードのレベルが1以上なら、相手に5ダメージを与える。』（CXのレベルは0として扱う。ダメージキャンセルは発生する）"
	],
	"specialAttrib": [
		"魔法",
		"竜"
	],
	"version": "3",
	"cardcode": "FT/S120-081S",
	"imageURL": "/wordpress/wp-content/images/cardlist/f/ft_s120/ft_s120_081s.png",
	"tags": null
}