{
	"set": "TF",
	"setName": "テラフォーマーズ",
	"side": "S",
	"release": "32",
	"id": "048",
	"name": "",
	"jpName": "最期の言葉",
	"cardType": "CX",
	"colour": "GREEN",
	"level": "-",
	"cost": "-",
	"power": "-",
	"soul": "0",
	"rarity": "CR",
	"breakDeckbuilding": false,
	"EN_Equivalent": false,
	"flavourText": "小町 小吉「…ああ伝わったよシーラ…」",
	"trigger": [
		"TREASURE"
	],
	"ability": [
		"【永】 あなたのキャラすべてに、パワーを＋1000し、ソウルを＋1。\u003cbr\u003e（[[treasure.gif]]：このカードがトリガーした時、あなたはこのカードを手札に戻す。あなたは自分の山札の上から1枚を、ストック置場に置いてよい）"
	],
	"specialAttrib": null,
	"version": "4",
	"cardcode": "TF/S32-048",
	"imageURL": "https://ws-tcg.com/wordpress/wp-content/images/t/tf_s32/tf_s32_048.png",
	"tags": null,
	"expansionId": 135
}