{
	"set": "MR",
	"setName": "マギアレコード 魔法少女まどか☆マギカ外伝",
	"side": "W",
	"release": "59",
	"id": "085",
	"name": "",
	"jpName": "織莉子への忠誠心 キリカ",
	"cardType": "CH",
	"colour": "BLUE",
	"level": "0",
	"cost": "0",
	"power": "2000",
	"soul": "1",
	"rarity": "U",
	"breakDeckbuilding": false,
	"EN_Equivalent": false,
	"flavourText": "",
	"trigger": [],
	"ability": [
		"【永】 このカードの下にマーカーがあるなら、このカードのレベルを＋1し、パワーを＋1500。",
		"【自】 このカードが手札から舞台に置かれた時、あなたは自分の山札の上から1枚を公開する。そのカードが《魔法》のキャラならこのカードの下にマーカーとして裏向きに置いてよい。（そうしないなら元に戻す）"
	],
	"specialAttrib": [
		"魔法",
		"ディフェンス"
	],
	"version": "2",
	"cardcode": "MR/W59-085"
}