{
	"set": "IM",
	"setName": "2009年度トライアルデッキ【S】",
	"side": "S",
	"release": "07",
	"id": "T06",
	"name": "",
	"jpName": "ハイタッチやよい",
	"cardType": "CH",
	"colour": "RED",
	"level": "2",
	"cost": "1",
	"power": "8500",
	"soul": "1",
	"rarity": "TD",
	"breakDeckbuilding": false,
	"EN_Equivalent": false,
	"flavourText": "",
	"trigger": [
		"SOUL"
	],
	"ability": [
		"【自】 このカードが手札から舞台に置かれた時、相手の「ハイタッチやよい」がいて、すべてのプレイヤーが認めたなら、ハイタッチする。そうしたら、すべてのプレイヤーは1枚引く。（音には注意しましょう）"
	],
	"specialAttrib": [
		"音楽",
		"カエル"
	],
	"version": "3",
	"cardcode": "IM/S07-T06",
	"imageURL": "/wordpress/wp-content/images/cardlist/i/im_s07/im_s07_t06.png",
	"tags": null
}