{
	"set": "RG",
	"setName": "2013年度トライアルデッキ【W】",
	"side": "W",
	"release": "26",
	"id": "T14",
	"name": "",
	"jpName": "超電磁砲",
	"cardType": "CX",
	"colour": "RED",
	"level": "0",
	"cost": "0",
	"power": "0",
	"soul": "0",
	"rarity": "TD",
	"breakDeckbuilding": false,
	"EN_Equivalent": false,
	"flavourText": "",
	"trigger": [
		"SOUL",
		"SOUL"
	],
	"ability": [
		"【永】 あなたのキャラすべてに、ソウルを+2。"
	],
	"specialAttrib": [],
	"version": "3",
	"cardcode": "RG/W26-T14",
	"imageURL": "/wordpress/wp-content/images/cardlist/r/rg_w26/rg_w26_t14.png",
	"tags": null
}