{
	"set": "AZL",
	"setName": "[TD]アズールレーン",
	"side": "S",
	"release": "102",
	"id": "T15",
	"name": "",
	"jpName": "ヨークタウン",
	"cardType": "CH",
	"colour": "BLUE",
	"level": "3",
	"cost": "2",
	"power": "9500",
	"soul": "2",
	"rarity": "TD",
	"breakDeckbuilding": false,
	"EN_Equivalent": false,
	"flavourText": "",
	"trigger": [
		"SOUL"
	],
	"ability": [
		"【自】 このカードが手札から舞台に置かれた時、あなたは自分のクロックの上から1枚を、控え室に置いてよい。",
		"【自】 このカードがアタックした時、あなたは自分の《艦船》のキャラを1枚選び、そのターン中、パワーを＋Ｘ。Ｘはあなたの《艦船》のキャラの枚数×500に等しい。"
	],
	"specialAttrib": [
		"艦船",
		"ユニオン"
	],
	"version": "3",
	"cardcode": "AZL/S102-T15",
	"imageURL": "/wordpress/wp-content/images/cardlist/a/azl_s102/azl_s102_t15.png",
	"tags": null
}