{
	"set": "LOD",
	"setName": "ロストディケイド",
	"side": "S",
	"release": "74",
	"id": "016",
	"name": "",
	"jpName": "世界の探索者 マルク",
	"cardType": "CH",
	"colour": "YELLOW",
	"level": "0",
	"cost": "0",
	"power": "2000",
	"soul": "1",
	"rarity": "C",
	"breakDeckbuilding": false,
	"EN_Equivalent": false,
	"flavourText": "さあ、次は世界のどこを調べようか！",
	"trigger": null,
	"ability": [
		"【自】 このカードがアタックした時、他のあなたの《冒険者》のキャラが2枚以上なら、そのターン中、このカードのパワーを＋2000。\u003cbr\u003e【自】 このカードのトリガーチェックでトリガーアイコンに[[soul.gif]]があるカードがでた時、そのターン中、このカードのソウルを＋1。"
	],
	"specialAttrib": [
		"冒険者"
	],
	"version": "4",
	"cardcode": "LOD/S74-016",
	"imageURL": "https://ws-tcg.com/wordpress/wp-content/images/l/lod_s74/lod_s74_016.png",
	"tags": null,
	"expansionId": 297
}