{
	"set": "SGS",
	"setName": "スクールガールストライカーズ",
	"side": "S",
	"release": "37",
	"id": "095",
	"name": "",
	"jpName": "理論派 真乃",
	"cardType": "CH",
	"colour": "RED",
	"level": "2",
	"cost": "2",
	"power": "10000",
	"soul": "1",
	"rarity": "C",
	"breakDeckbuilding": false,
	"EN_Equivalent": false,
	"flavourText": "これがゲームじゃない現実なんだって\u003cbr\u003eいつも自分に言い聞かせています",
	"trigger": [
		"SOUL"
	],
	"ability": [
		"【永】 このカードはサイドアタックできない。\u003cbr\u003e【永】 経験 あなたのレベル置場のカードのレベルの合計が3以上なら、このカードのパワーを＋1000。"
	],
	"specialAttrib": [
		"ストライカー",
		"カードゲーム"
	],
	"version": "4",
	"cardcode": "SGS/S37-095",
	"imageURL": "https://ws-tcg.com/wordpress/wp-content/images/s/sgs_s37/sgs_s37_095.png",
	"tags": null,
	"expansionId": 162
}