{
	"set": "CSM",
	"setName": "チェンソーマン",
	"side": "S",
	"release": "96",
	"id": "013",
	"name": "",
	"jpName": "乱戦 チェンソーマン",
	"cardType": "CH",
	"colour": "YELLOW",
	"level": "1",
	"cost": "0",
	"power": "5500",
	"soul": "1",
	"rarity": "U",
	"breakDeckbuilding": false,
	"EN_Equivalent": false,
	"flavourText": "",
	"trigger": [],
	"ability": [
		"【自】 このカードが手札から舞台に置かれた時、そのターン中、このカードのパワーを＋1500。",
		"【自】 このカードのバトル相手が【リバース】した時、あなたはそのキャラを思い出にする。"
	],
	"specialAttrib": [
		"デビルハンター",
		"公安"
	],
	"version": "3",
	"cardcode": "CSM/S96-013",
	"imageURL": "/wordpress/wp-content/images/cardlist/c/csm_s96/csm_s96_013.png",
	"tags": null
}