{
	"set": "MF",
	"setName": "劇場版マクロスＦ",
	"side": "S",
	"release": "13",
	"id": "037",
	"name": "",
	"jpName": "開拓重機 ランカ",
	"cardType": "CH",
	"colour": "GREEN",
	"level": "2",
	"cost": "1",
	"power": "6500",
	"soul": "1",
	"rarity": "U",
	"breakDeckbuilding": false,
	"EN_Equivalent": false,
	"flavourText": "",
	"trigger": [
		"SOUL"
	],
	"ability": [
		"【自】 チェンジ ［(2)このカードを控え室に置く］ あなたのアンコールステップの始めに、このカードが【レスト】しているなら、あなたはコストを払ってよい。そうしたら、あなたは自分の控え室の「“歌は魔法”ランカ」を1枚選び、このカードがいた枠に置く。（アンコールステップの始めにこのカードがいないなら発動しない）",
		"【起】［(1)］ あなたは自分のキャラを1枚選び、そのターン中、パワーを＋Ｘ。Ｘはそのキャラのレベル×500に等しい。"
	],
	"specialAttrib": [
		"音楽",
		"愛"
	],
	"version": "3",
	"cardcode": "MF/S13-037",
	"imageURL": "/wordpress/wp-content/images/cardlist/m/mf_s13/mf_s13_037.png",
	"tags": null
}