{
	"set": "RKN",
	"setName": "るろうに剣心 －明治剣客浪漫譚－",
	"side": "S",
	"release": "115",
	"id": "054",
	"name": "",
	"jpName": "不殺して守りきる 緋村剣心",
	"cardType": "CH",
	"colour": "RED",
	"level": "1",
	"cost": "1",
	"power": "3500",
	"soul": "1",
	"rarity": "U",
	"breakDeckbuilding": false,
	"EN_Equivalent": false,
	"flavourText": "",
	"trigger": [
		"SOUL"
	],
	"ability": [
		"【永】 あなたのターン中、他のあなたの《明治剣客浪漫譚》のキャラがいるなら、このカードのパワーを＋3000。",
		"【永】 このカードの正面のキャラのコストが0以下なら、このカードは【リバース】しない。"
	],
	"specialAttrib": [
		"明治剣客浪漫譚",
		"剣客"
	],
	"version": "3",
	"cardcode": "RKN/S115-054",
	"imageURL": "/wordpress/wp-content/images/cardlist/r/rkn_s115/rkn_s115_054.png",
	"tags": null
}