{
	"set": "NA",
	"setName": "魔法少女リリカルなのはA's",
	"side": "W",
	"release": "12",
	"id": "084",
	"name": "",
	"jpName": "“ヴォルケンリッター”ザフィーラ",
	"cardType": "CH",
	"colour": "BLUE",
	"level": "0",
	"cost": "0",
	"power": "1000",
	"soul": "1",
	"rarity": "U",
	"breakDeckbuilding": false,
	"EN_Equivalent": false,
	"flavourText": "夜天の主の下に集いし雲……",
	"trigger": null,
	"ability": [
		"【永】 他のあなたの前列の中央の枠のキャラに、パワーを＋1000。"
	],
	"specialAttrib": [
		"使い魔",
		"動物"
	],
	"version": "4",
	"cardcode": "NA/W12-084",
	"imageURL": "https://ws-tcg.com/wordpress/wp-content/images/n/na_w12/na_w12_084.png",
	"tags": null,
	"expansionId": 44
}