{
	"set": "GBS",
	"setName": "[TD+]ゴブリンスレイヤー",
	"side": "S",
	"release": "63",
	"id": "T08",
	"name": "",
	"jpName": "松明",
	"cardType": "EV",
	"colour": "RED",
	"level": "1",
	"cost": "0",
	"power": "0",
	"soul": "0",
	"rarity": "TD",
	"breakDeckbuilding": false,
	"EN_Equivalent": false,
	"flavourText": "",
	"trigger": [],
	"ability": [
		"【カウンター】 このカードは、あなたの《秩序》のキャラがいないなら、手札からプレイできない。",
		"あなたは自分の山札を上から4枚まで見て、《秩序》のキャラを1枚まで選んで相手に見せ、手札に加え、残りのカードを控え室に置く。"
	],
	"specialAttrib": [],
	"version": "3",
	"cardcode": "GBS/S63-T08",
	"imageURL": "/wordpress/wp-content/images/cardlist/g/gbs_s63/gbs_s63_t08.png",
	"tags": null
}