{
	"set": "LB",
	"setName": "アニメ「リトルバスターズ！」",
	"side": "W",
	"release": "21",
	"id": "037",
	"name": "",
	"jpName": "“凶器乱舞”鈴",
	"cardType": "CH",
	"colour": "GREEN",
	"level": "2",
	"cost": "1",
	"power": "8500",
	"soul": "1",
	"rarity": "C",
	"breakDeckbuilding": false,
	"EN_Equivalent": false,
	"flavourText": "いざ参る！　ぷらちな悪行三昧、成敗いたす！",
	"trigger": [
		"SOUL"
	],
	"ability": [
		"-"
	],
	"specialAttrib": [
		"動物",
		"武器"
	],
	"version": "4",
	"cardcode": "LB/W21-037",
	"imageURL": "https://ws-tcg.com/wordpress/wp-content/images/l/lb_w21/lb_w21_037.png",
	"tags": null,
	"expansionId": 96
}