{
	"set": "ZM",
	"setName": "ゼロの使い魔Ｆ",
	"side": "W",
	"release": "E13",
	"id": "45",
	"name": "",
	"jpName": "真実の鏡",
	"cardType": "CX",
	"colour": "BLUE",
	"level": "-",
	"cost": "-",
	"power": "-",
	"soul": "0",
	"rarity": "C",
	"breakDeckbuilding": false,
	"EN_Equivalent": false,
	"flavourText": "サイト「姫様！？」",
	"trigger": [
		"DRAW"
	],
	"ability": [
		"【永】 あなたのキャラすべてに、パワーを＋1000し、ソウルを＋1。",
		"（[[draw.gif]]：このカードがトリガーした時、あなたは1枚引いてよい）"
	],
	"specialAttrib": null,
	"version": "4",
	"cardcode": "ZM/WE13-45",
	"imageURL": "https://ws-tcg.com/wordpress/wp-content/images/z/zm_we13/zm_we13_45.png",
	"tags": null,
	"expansionId": 77
}