{
	"set": "DC",
	"setName": "ヴァイスシュヴァルツクロニクル D.C. D.C.II",
	"side": "W",
	"release": "C01",
	"id": "010",
	"name": "",
	"jpName": "巫女装束の音姫",
	"cardType": "CH",
	"colour": "YELLOW",
	"level": "2",
	"cost": "2",
	"power": "8000",
	"soul": "2",
	"rarity": "RE",
	"breakDeckbuilding": false,
	"EN_Equivalent": false,
	"flavourText": "",
	"trigger": [
		"SOUL"
	],
	"ability": [
		"【自】 【CXコンボ】 このカードがアタックした時、クライマックス置場に「存在のなくなる日」があるなら、あなたは相手のキャラを1枚選び、手札に戻してよい。",
		"【起】［(1)］ そのターン中、このカードのソウルを＋1。"
	],
	"specialAttrib": [
		"魔法",
		"巫女"
	],
	"version": "3",
	"cardcode": "DC/WC01-010",
	"imageURL": "/wordpress/wp-content/images/cardlist/d/dc_wc01/dc_wc01_010.png",
	"tags": null
}