{
	"set": "CHA",
	"setName": "Charlotte",
	"side": "W",
	"release": "40",
	"id": "052",
	"name": "",
	"jpName": "“大切な何か”美砂",
	"cardType": "CH",
	"colour": "RED",
	"level": "3",
	"cost": "2",
	"power": "9500",
	"soul": "2",
	"rarity": "RR",
	"breakDeckbuilding": false,
	"EN_Equivalent": false,
	"flavourText": "",
	"trigger": [
		"SOUL"
	],
	"ability": [
		"【自】 このカードが手札から舞台に置かれた時か『チェンジ』で舞台に置かれた時、あなたは自分のクロックの上から1枚を、控え室に置いてよい。",
		"【自】［(3)］ このカードがアタックした時、クライマックス置場に「恋と炎」があるなら、あなたはコストを払ってよい。そうしたら、相手に5ダメージを与える。（ダメージキャンセルは発生する）",
		"【自】 チェンジ ［このカードを控え室に置く］ あなたのクライマックスフェイズの始めに、あなたはコストを払ってよい。そうしたら、あなたは自分の控え室の「“大切な何か”西森 柚咲」を1枚選び、このカードがいた枠に置く。（クライマックスフェイズの始めにこのカードがいないなら発動しない）"
	],
	"specialAttrib": [
		"能力者",
		"死"
	],
	"version": "3",
	"cardcode": "CHA/W40-052",
	"imageURL": "/wordpress/wp-content/images/cardlist/c/cha_w40/cha_w40_052.png",
	"tags": null
}