{
	"set": "LRC",
	"setName": "リコリス・リコイル",
	"side": "W",
	"release": "105",
	"id": "002",
	"name": "",
	"jpName": "ウォールナットの正体 クルミ",
	"cardType": "CH",
	"colour": "YELLOW",
	"level": "0",
	"cost": "0",
	"power": "2000",
	"soul": "1",
	"rarity": "RR",
	"breakDeckbuilding": false,
	"EN_Equivalent": false,
	"flavourText": "",
	"trigger": [],
	"ability": [
		"【自】 あなたのクライマックスがクライマックス置場に置かれた時、あなたは相手の山札を上から2枚まで見て、山札の上に好きな順番で置く。",
		"【起】 集中 ［(1) このカードを【レスト】する］ あなたは自分の山札の上から4枚をめくり、控え室に置く。それらのカードのクライマックス1枚につき、あなたは自分の控え室の、《リコリコ》か《武器》のキャラを1枚まで選び、手札に戻す。"
	],
	"specialAttrib": [
		"リコリコ",
		"ネット"
	],
	"version": "3",
	"cardcode": "LRC/W105-002",
	"imageURL": "/wordpress/wp-content/images/cardlist/l/lrc_w105/lrc_w105_002.png",
	"tags": null
}