{
	"set": "LRC",
	"setName": "リコリス・リコイル",
	"side": "W",
	"release": "105",
	"id": "035",
	"name": "",
	"jpName": "帰る居場所 千束",
	"cardType": "CH",
	"colour": "RED",
	"level": "3",
	"cost": "2",
	"power": "8000",
	"soul": "2",
	"rarity": "RR",
	"breakDeckbuilding": false,
	"EN_Equivalent": false,
	"flavourText": "たきな　ありがと",
	"trigger": [
		"SOUL"
	],
	"ability": [
		"【永】 あなたの、《リコリコ》か《武器》のキャラが4枚以上なら、あなたの手札のこのカードのレベルを－1。\u003cbr\u003e【自】 このカードが手札から舞台に置かれた時、あなたは自分のクロックの上から1枚を、控え室に置いてよい。\u003cbr\u003e【自】 このカードが手札から舞台に置かれた時、あなたの控え室に「選んだ居場所 たきな」があるなら、次の相手のターンの終わりまで、このカードのパワーを＋3000。"
	],
	"specialAttrib": [
		"リコリコ",
		"武器"
	],
	"version": "4",
	"cardcode": "LRC/W105-035",
	"imageURL": "https://ws-tcg.com/wordpress/wp-content/images/l/lrc_w105/lrc_w105_035.png",
	"tags": null,
	"expansionId": 426
}