{
	"set": "IMC",
	"setName": "PRカード【Wサイド】",
	"side": "W",
	"release": "115",
	"id": "P01",
	"name": "",
	"jpName": "ラブレター 島村卯月",
	"cardType": "CH",
	"colour": "RED",
	"level": "0",
	"cost": "0",
	"power": "1000",
	"soul": "1",
	"rarity": "PR",
	"breakDeckbuilding": false,
	"EN_Equivalent": false,
	"flavourText": "",
	"trigger": [],
	"ability": [
		"【自】 このカードが手札から舞台に置かれた時、あなたは自分の《音楽》のキャラを1枚選び、そのターン中、パワーを＋1500。",
		"【自】 このカードがアタックした時、あなたは自分の《音楽》のキャラを1枚選び、そのターン中、パワーを＋1500。"
	],
	"specialAttrib": [
		"音楽",
		"笑顔"
	],
	"version": "3",
	"cardcode": "IMC/W115-P01",
	"imageURL": "/wordpress/wp-content/images/cardlist/i/imc_w115/imc_w115_p01.png",
	"tags": null
}