{
	"set": "MG",
	"setName": "\u003c物語\u003eシリーズ セカンドシーズン",
	"side": "S",
	"release": "39",
	"id": "085",
	"name": "",
	"jpName": "元人間 斧乃木余接",
	"cardType": "CH",
	"colour": "BLUE",
	"level": "1",
	"cost": "0",
	"power": "1000",
	"soul": "1",
	"rarity": "U",
	"breakDeckbuilding": false,
	"EN_Equivalent": false,
	"flavourText": "",
	"trigger": [],
	"ability": [
		"【自】［(1)］ あなたがこのカードの『助太刀』を使った時、あなたはコストを払ってよい。そうしたら、あなたは自分のレベル1以下のカード名に「暦」か「真宵」を含むキャラを1枚選び、思い出にし、次のあなたのドローフェイズの始めに、あなたは自分の思い出置場のそのキャラを、舞台の好きな枠に置く。",
		"【起】【カウンター】 助太刀1000 レベル1 ［手札のこのカードを控え室に置く］ （あなたは自分のフロントアタックされているキャラを1枚選び、そのターン中、パワーを＋1000）",
		""
	],
	"specialAttrib": [
		"怪異",
		"人形"
	],
	"version": "2",
	"cardcode": "MG/S39-085"
}