{
	"set": "MG",
	"setName": "\u003c物語\u003eシリーズ セカンドシーズン",
	"side": "S",
	"release": "39",
	"id": "015",
	"name": "",
	"jpName": "時間移動 阿良々木暦",
	"cardType": "CH",
	"colour": "YELLOW",
	"level": "0",
	"cost": "0",
	"power": "1000",
	"soul": "1",
	"rarity": "C",
	"breakDeckbuilding": false,
	"EN_Equivalent": false,
	"flavourText": "",
	"trigger": [],
	"ability": [
		"【自】 絆／「昔話 忍野忍」 ［(1)］ （このカードがプレイされて舞台に置かれた時、あなたはコストを払ってよい。そうしたら、あなたは自分の控え室の「昔話 忍野忍」を1枚選び、手札に戻す）"
	],
	"specialAttrib": [
		"怪異",
		"血"
	],
	"version": "3",
	"cardcode": "MG/S39-015",
	"imageURL": "/wordpress/wp-content/images/cardlist/m/mg_s39/mg_s39_015.png",
	"tags": null
}