{
	"set": "KMN",
	"setName": "けものフレンズ",
	"side": "W",
	"release": "51",
	"id": "055",
	"name": "",
	"jpName": "かまどの火",
	"cardType": "EV",
	"colour": "GREEN",
	"level": "2",
	"cost": "0",
	"power": "-",
	"soul": "0",
	"rarity": "U",
	"breakDeckbuilding": false,
	"EN_Equivalent": false,
	"flavourText": "-",
	"trigger": null,
	"ability": [
		"【カウンター】 あなたは自分のキャラを1枚選び、手札に戻す。"
	],
	"specialAttrib": null,
	"version": "4",
	"cardcode": "KMN/W51-055",
	"imageURL": "https://ws-tcg.com/wordpress/wp-content/images/k/kmn_w51/kmn_w51_055.png",
	"tags": null,
	"expansionId": 205
}