{
	"set": "PXR",
	"setName": "Toy Story 30YEARS＆BEYOND",
	"side": "S",
	"release": "122",
	"id": "030",
	"name": "",
	"jpName": "ドクター・ポークチョップ",
	"cardType": "CH",
	"colour": "YELLOW",
	"level": "2",
	"cost": "1",
	"power": "3500",
	"soul": "1",
	"rarity": "C",
	"breakDeckbuilding": false,
	"EN_Equivalent": false,
	"flavourText": "",
	"trigger": [
		"SOUL"
	],
	"ability": [
		"【永】 あなたのターン中、他のあなたの《PIXAR》のキャラすべてに、パワーを＋Ｘ。Ｘはあなたのレベル×1000に等しい。",
		"【起】［このカードを【レスト】する］ あなたは1枚引き、自分の手札を1枚選び、控え室に置く。"
	],
	"specialAttrib": [
		"PIXAR"
	],
	"version": "3",
	"cardcode": "PXR/S122-030",
	"imageURL": "/wordpress/wp-content/images/cardlist/p/pxr_s122/pxr_s122_030.png",
	"tags": null
}