{
	"set": "Ksm",
	"setName": "Key all-star",
	"side": "W",
	"release": "102",
	"id": "061",
	"name": "",
	"jpName": "“サマードレス” 識",
	"cardType": "CH",
	"colour": "RED",
	"level": "2",
	"cost": "1",
	"power": "5000",
	"soul": "1",
	"rarity": "U",
	"breakDeckbuilding": false,
	"EN_Equivalent": false,
	"flavourText": "",
	"trigger": [
		"SOUL"
	],
	"ability": [
		"【永】 応援 このカードの前のあなたのレベル3以上のキャラすべてに、パワーを＋2000。",
		"【起】［手札のイベントを1枚控え室に置き、このカードを【レスト】する］ あなたは自分のクロックの上から1枚を、控え室に置く。"
	],
	"specialAttrib": [
		"Anniversary",
		"サマポケ",
		"鬼"
	],
	"version": "3",
	"cardcode": "Ksm/W102-061",
	"imageURL": "/wordpress/wp-content/images/cardlist/k/key_w102/ksm_w102_061.png",
	"tags": null
}