{
	"set": "DCT",
	"setName": "[TD+]D_CIDE TRAUMEREI",
	"side": "S",
	"release": "86",
	"id": "T10",
	"name": "",
	"jpName": "道はただ延々と",
	"cardType": "CX",
	"colour": "YELLOW",
	"level": "0",
	"cost": "0",
	"power": "0",
	"soul": "0",
	"rarity": "TD",
	"breakDeckbuilding": false,
	"EN_Equivalent": false,
	"flavourText": "",
	"trigger": [
		"CHOICE"
	],
	"ability": [
		"【永】 あなたのキャラすべてに、パワーを＋1000し、ソウルを＋1。",
		"（[CHOICE]があるキャラを1枚選び、手札に戻すかストック置場に置いてよい）"
	],
	"specialAttrib": [],
	"version": "3",
	"cardcode": "DCT/S86-T10",
	"imageURL": "/wordpress/wp-content/images/cardlist/d/dct_s86/dct_s86_t10.png",
	"tags": null
}