{
	"set": "IMS",
	"setName": "アイドルマスター ミリオンライブ！ Welcome to the New St@ge",
	"side": "S",
	"release": "93",
	"id": "022",
	"name": "",
	"jpName": "柔らかな眼差し　島原エレナ",
	"cardType": "CH",
	"colour": "YELLOW",
	"level": "0",
	"cost": "0",
	"power": "2000",
	"soul": "1",
	"rarity": "U",
	"breakDeckbuilding": false,
	"EN_Equivalent": false,
	"flavourText": "",
	"trigger": [],
	"ability": [
		"【永】 あなたのストックが2枚以下なら、このカードのパワーを＋1500。",
		"【自】 このカードのバトル相手が【リバース】した時、他のあなたの《音楽》のキャラがいるなら、あなたは相手の前列のレベル0以下のキャラを1枚選び、控え室に置いてよい。"
	],
	"specialAttrib": [
		"音楽",
		"サンバ"
	],
	"version": "2",
	"cardcode": "IMS/S93-022"
}