{
	"set": "DG",
	"setName": "魔界戦記ディスガイア4",
	"side": "S",
	"release": "E08",
	"id": "18",
	"name": "",
	"jpName": "断罪者 ネモ",
	"cardType": "CH",
	"colour": "GREEN",
	"level": "0",
	"cost": "0",
	"power": "2000",
	"soul": "1",
	"rarity": "C",
	"breakDeckbuilding": false,
	"EN_Equivalent": false,
	"flavourText": "",
	"trigger": [],
	"ability": [
		"【自】 バトル中のこのカードが【リバース】した時、あなたは相手のクロックを1枚選び、控え室に置いてよい。そうしたら、相手は自分の山札の上から1枚を、クロック置場に置く。"
	],
	"specialAttrib": [
		"霊",
		"メガネ"
	],
	"version": "3",
	"cardcode": "DG/SE08-18",
	"imageURL": "/wordpress/wp-content/images/cardlist/d/dg_se08/dg_se08_18.png",
	"tags": null
}