{
	"set": "DG",
	"setName": "PRカード【Sサイド】",
	"side": "S",
	"release": "E08",
	"id": "52",
	"name": "",
	"jpName": "夢の中でも奮闘中 フーカ",
	"cardType": "CH",
	"colour": "YELLOW",
	"level": "0",
	"cost": "0",
	"power": "2500",
	"soul": "1",
	"rarity": "PR",
	"breakDeckbuilding": false,
	"EN_Equivalent": false,
	"flavourText": "元気ですかーーーッ！！",
	"trigger": null,
	"ability": [
		"【永】 他のあなたの《プリニー》のキャラが2枚以上なら、このカードのパワーを＋1000。"
	],
	"specialAttrib": [
		"プリニー",
		"死"
	],
	"version": "4",
	"cardcode": "DG/SE08-52",
	"imageURL": "https://ws-tcg.com/wordpress/wp-content/images/d/dg_se08/dg_se08_52.png",
	"tags": null,
	"expansionId": 13
}