{
	"set": "FS",
	"setName": "劇場版「Fate/stay night [Heaven’s Feel]」",
	"side": "S",
	"release": "64",
	"id": "061",
	"name": "",
	"jpName": "黒い影",
	"cardType": "CH",
	"colour": "RED",
	"level": "1",
	"cost": "1",
	"power": "2500",
	"soul": "1",
	"rarity": "R",
	"breakDeckbuilding": false,
	"EN_Equivalent": false,
	"flavourText": "",
	"trigger": [
		"SOUL"
	],
	"ability": [
		"【永】 応援 このカードの前のあなたのキャラすべてに、次の能力を与える。『【自】 バトル中のこのカードが【リバース】した時、あなたのストックが相手のストックより少ないなら、あなたはこのカードをストック置場に置いてよい。』",
		"【永】 このカードの下にマーカーがあり、あなたのレベルが2以上なら、このカードは次の能力を得る。『【起】［(1) このカードを控え室に置く］ あなたは自分の控え室の「圧倒する力 セイバーオルタ」を1枚選び、舞台の好きな枠に置く。』"
	],
	"specialAttrib": [
		"謎",
		"影"
	],
	"version": "2",
	"cardcode": "FS/S64-061"
}