{
	"set": "Woo",
	"setName": "【スペシャルセット】うーさーのその日暮らし",
	"side": "S",
	"release": "E19",
	"id": "012",
	"name": "",
	"jpName": "召喚されし勇者 うーさー",
	"cardType": "CH",
	"colour": "YELLOW",
	"level": "2",
	"cost": "1",
	"power": "9000",
	"soul": "1",
	"rarity": "TD",
	"breakDeckbuilding": false,
	"EN_Equivalent": false,
	"flavourText": "",
	"trigger": [
		"SOUL"
	],
	"ability": [
		"【永】 このカードは、あなたのキャラが3枚以下なら、手札からプレイできない。"
	],
	"specialAttrib": [
		"謎",
		"へたれ"
	],
	"version": "3",
	"cardcode": "Woo/SE19-012",
	"imageURL": "/wordpress/wp-content/images/cardlist/w/woo_se19/woo_se19_012.png",
	"tags": null
}