{
	"set": "LL",
	"setName": "ラブライブ！",
	"side": "W",
	"release": "24",
	"id": "097",
	"name": "",
	"jpName": "練習日和？",
	"cardType": "EV",
	"colour": "BLUE",
	"level": "2",
	"cost": "1",
	"power": "-",
	"soul": "0",
	"rarity": "U",
	"breakDeckbuilding": false,
	"EN_Equivalent": false,
	"flavourText": "ザーー！！",
	"trigger": null,
	"ability": [
		"あなたは自分の山札を見て《音楽》のキャラを2枚まで選んで相手に見せ、手札に加え、その山札をシャッフルする。あなたは自分の手札を1枚選び、控え室に置く。"
	],
	"specialAttrib": null,
	"version": "4",
	"cardcode": "LL/W24-097",
	"imageURL": "https://ws-tcg.com/wordpress/wp-content/images/l/ll_w24/ll_w24_097.png",
	"tags": null,
	"expansionId": 98
}