{
	"set": "THP",
	"setName": "東方Project ～ Black and White Lotus Land.",
	"side": "S",
	"release": "130",
	"id": "022",
	"name": "",
	"jpName": "愉快な忘れ傘 小傘",
	"cardType": "CH",
	"colour": "YELLOW",
	"level": "1",
	"cost": "1",
	"power": "1000",
	"soul": "1",
	"rarity": "C",
	"breakDeckbuilding": false,
	"EN_Equivalent": false,
	"flavourText": "無駄こそが美しさ 予定通りの人生は悪夢のような物よ\u003cbr\u003e（「東方星蓮船　～ Undefined Fantastic Object.」より）",
	"trigger": [
		"SOUL"
	],
	"ability": [
		"【自】 あなたがこのカードの『助太刀』を使った時、あなたの《幻想郷》のキャラがいるなら、あなたは自分か相手の、山札の上から3枚を、控え室に置く。\u003cbr\u003e【起】【カウンター】 助太刀2000 レベル1 ［(1) 手札のこのカードを控え室に置く］ （あなたは自分のフロントアタックされているキャラを1枚選び、そのターン中、パワーを＋2000）"
	],
	"specialAttrib": [
		"幻想郷",
		"命蓮寺"
	],
	"version": "4",
	"cardcode": "THP/S130-022",
	"imageURL": "https://ws-tcg.com/wordpress/wp-content/images/cardlist/t/thp_s130/thp_s130_022.png",
	"tags": null,
	"expansionId": 552
}