{
	"set": "THP",
	"setName": "",
	"side": "S",
	"release": "130",
	"id": "061SP",
	"name": "",
	"jpName": "快晴の巫女 霊夢",
	"cardType": "CH",
	"colour": "RED",
	"level": "1",
	"cost": "0",
	"power": "3500",
	"soul": "1",
	"rarity": "SP",
	"breakDeckbuilding": false,
	"EN_Equivalent": false,
	"flavourText": "-",
	"trigger": null,
	"ability": [
		"【永】 あなたのターン中、あなたのキャラすべてが《幻想郷》なら、このカードのパワーを＋4000。\u003cbr\u003e【自】【CXコンボ】 このカードのアタックの終わりに、CX置場に「夢符「封魔陣」」があるなら、あなたは自分の山札の上から1枚を公開し、自分の控え室のレベルＸ以下の《幻想郷》のキャラを1枚まで選び、手札に戻すかストック置場に置き、公開したカードが「少女綺想曲　～ Dream Battle 霊夢」かレベル1以上のカードなら、次の相手のターンの終わりまで、このカードは次の能力を得る。『【自】 このカードがフロントアタックされた時、あなたはこのカードを手札に戻してよい。』Ｘは公開されたカードのレベルに等しい。（CXのレベルは0として扱う。公開したカードは元に戻す）"
	],
	"specialAttrib": [
		"幻想郷",
		"博麗神社"
	],
	"version": "3",
	"cardcode": "THP/S130-061SP",
	"imageURL": "https://ws-tcg.com/wordpress/wp-content/images/t/thp_s130/thp_s130_061sp.png",
	"tags": null,
	"expansionId": 552
}