{
	"set": "FZ",
	"setName": "2012年度トライアルデッキ【S】",
	"side": "S",
	"release": "17",
	"id": "102",
	"name": "",
	"jpName": "ダークスーツのセイバー",
	"cardType": "CH",
	"colour": "YELLOW",
	"level": "2",
	"cost": "1",
	"power": "8000",
	"soul": "1",
	"rarity": "TD",
	"breakDeckbuilding": false,
	"EN_Equivalent": false,
	"flavourText": "",
	"trigger": [
		"SOUL"
	],
	"ability": [
		"【起】［あなたのキャラを2枚【レスト】する］ そのターン中、このカードのパワーを＋2000。"
	],
	"specialAttrib": [
		"サーヴァント",
		"王族"
	],
	"version": "3",
	"cardcode": "FZ/S17-102",
	"imageURL": "/wordpress/wp-content/images/cardlist/f/fz_s17/fz_s17_102.png",
	"tags": null
}