{
	"set": "BD",
	"setName": "プレミアムブースター BanG Dream! 10th Anniversary！",
	"side": "W",
	"release": "E49",
	"id": "45SP",
	"name": "",
	"jpName": "“その身にまとうのは”白金燐子",
	"cardType": "CH",
	"colour": "BLUE",
	"level": "0",
	"cost": "0",
	"power": "1500",
	"soul": "1",
	"rarity": "SP",
	"breakDeckbuilding": false,
	"EN_Equivalent": false,
	"flavourText": "",
	"trigger": [],
	"ability": [
		"【永】 応援 あなたのターン中、このカードの前のあなたのレベル1以上のキャラすべてに、パワーを＋500。",
		"【起】 集中 ［(1) このカードを【レスト】する］ あなたは自分の山札の上から4枚をめくり、控え室に置く。それらのカードのCX1枚につき、あなたは自分の控え室のキャラを1枚まで選び、手札に戻す。"
	],
	"specialAttrib": [
		"Anniversary",
		"音楽",
		"Roselia"
	],
	"version": "3",
	"cardcode": "BD/WE49-45SP",
	"imageURL": "/wordpress/wp-content/images/cardlist/b/bd_we49/bd_we49_45sp.png",
	"tags": null
}