{
	"set": "IM",
	"setName": "劇場版『THE IDOLM@STER MOVIE 輝きの向こう側へ！』",
	"side": "S",
	"release": "30",
	"id": "046",
	"name": "",
	"jpName": "皆を想うあずさ",
	"cardType": "CH",
	"colour": "GREEN",
	"level": "2",
	"cost": "1",
	"power": "7500",
	"soul": "1",
	"rarity": "C",
	"breakDeckbuilding": false,
	"EN_Equivalent": false,
	"flavourText": "",
	"trigger": [
		"SOUL"
	],
	"ability": [
		"【永】 他のあなたの、《愛》か《占い》のキャラが2枚以上なら、このカードのパワーを＋1000。",
		"【自】 この能力は1ターンにつき2回まで発動する。他のあなたの、《愛》か《占い》のキャラが手札から舞台に置かれた時、そのターン中、このカードのパワーを＋1000。"
	],
	"specialAttrib": [
		"音楽",
		"愛"
	],
	"version": "2",
	"cardcode": "IM/S30-046"
}