{
	"set": "IMC",
	"setName": "プレミアムブースター アイドルマスター シンデレラガールズ",
	"side": "W",
	"release": "E51",
	"id": "23M@P",
	"name": "",
	"jpName": "WINTER and WINDOW",
	"cardType": "CX",
	"colour": "YELLOW",
	"level": "-",
	"cost": "-",
	"power": "-",
	"soul": "0",
	"rarity": "M@P",
	"breakDeckbuilding": false,
	"EN_Equivalent": false,
	"flavourText": "-",
	"trigger": [
		"CHOICE"
	],
	"ability": [
		"【永】 あなたのキャラすべてに、パワーを＋1000し、ソウルを＋1。\u003cbr\u003e（[[choice.gif]]：このカードがトリガーした時、あなたは自分の控え室のトリガーアイコンに[[soul.gif]]があるキャラを1枚選び、手札に戻すかストック置場に置いてよい）"
	],
	"specialAttrib": null,
	"version": "4",
	"cardcode": "IMC/WE51-23M@P",
	"imageURL": "https://ws-tcg.com/wordpress/wp-content/images/i/imc_we51/imc_we51_23m@p.png",
	"tags": null,
	"expansionId": 539
}