{
	"set": "P4",
	"setName": "TVアニメ「ペルソナ４」",
	"side": "S",
	"release": "E12",
	"id": "47",
	"name": "",
	"jpName": "現役美少女アイドル",
	"cardType": "CX",
	"colour": "GREEN",
	"level": "0",
	"cost": "0",
	"power": "0",
	"soul": "0",
	"rarity": "RE",
	"breakDeckbuilding": false,
	"EN_Equivalent": false,
	"flavourText": "",
	"trigger": [
		"SOUL",
		"SOUL"
	],
	"ability": [
		"【自】 このカードが手札からクライマックス置場に置かれた時、あなたは1枚引き、自分のキャラを1枚選び、そのターン中、ソウルを＋3。"
	],
	"specialAttrib": [],
	"version": "2",
	"cardcode": "P4/SE12-47"
}