{
	"set": "P4",
	"setName": "TVアニメ「ペルソナ４」",
	"side": "S",
	"release": "E12",
	"id": "40",
	"name": "",
	"jpName": "堂島 遼太郎",
	"cardType": "CH",
	"colour": "YELLOW",
	"level": "1",
	"cost": "1",
	"power": "2500",
	"soul": "1",
	"rarity": "RE",
	"breakDeckbuilding": false,
	"EN_Equivalent": false,
	"flavourText": "",
	"trigger": [
		"SOUL"
	],
	"ability": [
		"【自】 このカードが手札から舞台に置かれた時、あなたは自分の、《勇者》かカード名に「主人公」を含むキャラを1枚選び、そのターン中、パワーを＋3000し、ソウルを＋1。",
		"【自】 あなたのターンの終わりに、あなたの思い出置場にキャラがあるなら、このカードを手札に戻す。"
	],
	"specialAttrib": [
		"警察"
	],
	"version": "2",
	"cardcode": "P4/SE12-40"
}