{
	"set": "SHS",
	"setName": "冴えない彼女の育てかた Fine",
	"side": "W",
	"release": "98",
	"id": "102",
	"name": "",
	"jpName": "Happy Life 出海",
	"cardType": "CH",
	"colour": "YELLOW",
	"level": "0",
	"cost": "0",
	"power": "1000",
	"soul": "1",
	"rarity": "PR",
	"breakDeckbuilding": false,
	"EN_Equivalent": false,
	"flavourText": "",
	"trigger": [],
	"ability": [
		"【自】 このカードの与えたダメージがキャンセルされなかった時、そのターン中、このカードのパワーを＋6000。"
	],
	"specialAttrib": [
		"ゲーム",
		"漫画"
	],
	"version": "2",
	"cardcode": "SHS/W98-102"
}