{
	"set": "RN",
	"setName": "ロボティクス・ノーツ",
	"side": "W",
	"release": "16",
	"id": "005",
	"name": "",
	"jpName": "命の恩人 あき穂",
	"cardType": "CH",
	"colour": "YELLOW",
	"level": "1",
	"cost": "0",
	"power": "3000",
	"soul": "1",
	"rarity": "R",
	"breakDeckbuilding": false,
	"EN_Equivalent": false,
	"flavourText": "",
	"trigger": [],
	"ability": [
		"【永】 他のあなたの《科学》のキャラすべてに、パワーを＋500。",
		"【起】［あなたの山札の上から1枚をクロック置場に置き、あなたのキャラを2枚【レスト】する］ あなたは自分の控え室の「ある夏の日 海翔」を1枚選び、舞台の好きな枠に置く。"
	],
	"specialAttrib": [
		"科学",
		"メカ"
	],
	"version": "2",
	"cardcode": "RN/W16-005"
}