{
	"set": "DG",
	"setName": "魔界戦記ディスガイア",
	"side": "S",
	"release": "02",
	"id": "098",
	"name": "",
	"jpName": "新婚女王",
	"cardType": "CX",
	"colour": "BLUE",
	"level": "-",
	"cost": "-",
	"power": "-",
	"soul": "0",
	"rarity": "CR",
	"breakDeckbuilding": false,
	"EN_Equivalent": false,
	"flavourText": "そして、人間界に帰ったボクらを待っていたのは―――",
	"trigger": [
		"SOUL",
		"SOUL"
	],
	"ability": [
		"【永】あなたのキャラすべてに、ソウルを＋2。"
	],
	"specialAttrib": null,
	"version": "4",
	"cardcode": "DG/S02-098",
	"imageURL": "https://ws-tcg.com/wordpress/wp-content/images/d/dg_s02/dg_s02_098.png",
	"tags": null,
	"expansionId": 5
}