{
	"set": "PY",
	"setName": "ぷよぷよ",
	"side": "S",
	"release": "38",
	"id": "006S",
	"name": "",
	"jpName": "セクシーな格闘女王 ルルー",
	"cardType": "CH",
	"colour": "YELLOW",
	"level": "1",
	"cost": "0",
	"power": "6000",
	"soul": "1",
	"rarity": "SR",
	"breakDeckbuilding": false,
	"EN_Equivalent": false,
	"flavourText": "SECRET",
	"trigger": null,
	"ability": [
		"【永】 このカードはサイドアタックできない。"
	],
	"specialAttrib": [
		"ぷよ",
		"愛"
	],
	"version": "4",
	"cardcode": "PY/S38-006S",
	"imageURL": "https://ws-tcg.com/wordpress/wp-content/images/p/py_s38/py_s38_006s.png",
	"tags": null,
	"expansionId": 160
}