{
	"set": "KF",
	"setName": "2009年度トライアルデッキ【S】",
	"side": "S",
	"release": "05",
	"id": "T06",
	"name": "",
	"jpName": "完全勝利",
	"cardType": "CX",
	"colour": "YELLOW",
	"level": "0",
	"cost": "0",
	"power": "0",
	"soul": "0",
	"rarity": "TD",
	"breakDeckbuilding": false,
	"EN_Equivalent": false,
	"flavourText": "",
	"trigger": [
		"SOUL",
		"RETURN"
	],
	"ability": [
		"【永】 あなたのキャラすべてに、パワーを＋1000し、ソウルを＋1。",
		"（[RETURN]：このカードがトリガーした時、あなたは相手のキャラを1枚選び、手札に戻してよい）"
	],
	"specialAttrib": [],
	"version": "3",
	"cardcode": "KF/S05-T06",
	"imageURL": "/wordpress/wp-content/images/cardlist/k/kf_s05/kf_s05_t06.png",
	"tags": null
}