{
	"set": "RZ",
	"setName": "「Re:ゼロから始める異世界生活」Vol.3",
	"side": "S",
	"release": "116",
	"id": "013S",
	"name": "",
	"jpName": "“憤怒の魔女” ミネルヴァ",
	"cardType": "CH",
	"colour": "YELLOW",
	"level": "3",
	"cost": "2",
	"power": "9500",
	"soul": "2",
	"rarity": "SR",
	"breakDeckbuilding": false,
	"EN_Equivalent": false,
	"flavourText": "",
	"trigger": [
		"SOUL"
	],
	"ability": [
		"【永】 あなたのターン中、他のあなたの、《魔法》か《武器》のキャラが4枚以上なら、このカードのパワーを＋5000し、このカードは次の能力を得る。『【永】 このカードのバトル中、相手はイベントと『助太刀』を手札からプレイできない。』",
		"【自】［(1)］ このカードがアタックした時、あなたのキャラすべてが《魔法》か《武器》なら、あなたはコストを払ってよい。そうしたら、あなたは相手に1ダメージを与えるか、自分のクロックの上から1枚を、控え室に置く。（ダメージキャンセルは発生する）"
	],
	"specialAttrib": [
		"魔法",
		"魔女"
	],
	"version": "3",
	"cardcode": "RZ/S116-013S",
	"imageURL": "/wordpress/wp-content/images/cardlist/r/rz_s116/rz_s116_013s.png",
	"tags": null
}