{
	"set": "EV",
	"setName": "ヱヴァンゲリヲン新劇場版",
	"side": "S",
	"release": "12",
	"id": "029SP",
	"name": "",
	"jpName": "極秘入国者 マリ",
	"cardType": "CH",
	"colour": "GREEN",
	"level": "0",
	"cost": "0",
	"power": "2000",
	"soul": "1",
	"rarity": "SP",
	"breakDeckbuilding": false,
	"EN_Equivalent": false,
	"flavourText": "",
	"trigger": [],
	"ability": [
		"【自】 このカードが手札から舞台に置かれた時、あなたは自分の《パイロット》のキャラを1枚選び、そのターン中、パワーを＋1500。"
	],
	"specialAttrib": [
		"パイロット",
		"メガネ"
	],
	"version": "3",
	"cardcode": "EV/S12-029SP",
	"imageURL": "/wordpress/wp-content/images/cardlist/e/ev_s12/ev_s12_029sp.png",
	"tags": null
}