{
	"set": "DJ",
	"setName": "[TD]D4DJ Groovy Mix Peaky P-key \u0026 Photon Maiden",
	"side": "S",
	"release": "97",
	"id": "T23",
	"name": "",
	"jpName": "新たなステージへ！ 清水絵空",
	"cardType": "CH",
	"colour": "RED",
	"level": "0",
	"cost": "0",
	"power": "2500",
	"soul": "1",
	"rarity": "TD",
	"breakDeckbuilding": false,
	"EN_Equivalent": false,
	"flavourText": "",
	"trigger": [],
	"ability": [
		"【自】 このカードが手札から舞台に置かれた時、あなたは自分の山札の上から2枚を、控え室に置き、そのターン中、このカードのパワーを＋Ｘ。Ｘはそれらのカードの《音楽》のキャラの枚数×1000に等しい。"
	],
	"specialAttrib": [],
	"version": "2",
	"cardcode": "DJ/S97-T23"
}