{
	"set": "BD",
	"setName": "MyGO!!!!! × Ave Mujica",
	"side": "W",
	"release": "125",
	"id": "006S",
	"name": "",
	"jpName": "芸能人の娘 若葉睦",
	"cardType": "CH",
	"colour": "GREEN",
	"level": "2",
	"cost": "0",
	"power": "1500",
	"soul": "1",
	"rarity": "SR",
	"breakDeckbuilding": false,
	"EN_Equivalent": false,
	"flavourText": "",
	"trigger": [
		"SOUL"
	],
	"ability": [
		"【自】 このカードが手札から舞台に置かれた時、あなたは1枚引いてよい。そうしたら、あなたは自分の手札を1枚選び、控え室に置く。",
		"【自】 このカードが手札から舞台に置かれた時、あなたは自分の控え室の「隠した素顔 モーティス」を1枚選び、このカードの下にマーカーとして表向きに置いてよい。",
		"【自】 あなたのCXフェイズの始めに、あなたはこのカードのマーカーの「隠した素顔 モーティス」を1枚選び、このカードがいる枠に置いてよい。"
	],
	"specialAttrib": [
		"音楽",
		"Ave Mujica"
	],
	"version": "3",
	"cardcode": "BD/W125-006S",
	"imageURL": "/wordpress/wp-content/images/cardlist/b/bd_w125/bd_w125_006s.png",
	"tags": null
}