{
	"set": "PP",
	"setName": "PSYCHO-PASS サイコパス",
	"side": "S",
	"release": "E14",
	"id": "27",
	"name": "",
	"jpName": "槙島 聖護",
	"cardType": "CH",
	"colour": "BLUE",
	"level": "3",
	"cost": "2",
	"power": "9000",
	"soul": "2",
	"rarity": "R",
	"breakDeckbuilding": false,
	"EN_Equivalent": false,
	"flavourText": "",
	"trigger": [
		"SOUL"
	],
	"ability": [
		"【永】 他のあなたの《サイコパス》のキャラ1枚につき、このカードのパワーを＋500。",
		"【自】 このカードが手札から舞台に置かれた時か『チェンジ』で舞台に置かれた時、あなたは2枚まで引き、自分の手札を1枚選び、控え室に置く。",
		"【自】［手札を1枚控え室に置く］ あなたのクライマックス置場に「対峙するふたり」が置かれた時、前列にこのカードがいるなら、あなたはコストを払ってよい。そうしたら、あなたは相手のコスト1以下のキャラを1枚選び、山札の下に置く。"
	],
	"specialAttrib": [
		"サイコパス",
		"本"
	],
	"version": "3",
	"cardcode": "PP/SE14-27",
	"imageURL": "/wordpress/wp-content/images/cardlist/p/pp_se14/pp_se14_27.png",
	"tags": null
}