{
	"set": "LB",
	"setName": "リトルバスターズ!",
	"side": "W",
	"release": "02",
	"id": "100",
	"name": "",
	"jpName": "２つの長い影",
	"cardType": "CX",
	"colour": "BLUE",
	"level": "-",
	"cost": "-",
	"power": "-",
	"soul": "0",
	"rarity": "CC",
	"breakDeckbuilding": false,
	"EN_Equivalent": false,
	"flavourText": "…わたしと同じリズムです",
	"trigger": [
		"SOUL",
		"SOUL"
	],
	"ability": [
		"【永】 あなたのキャラすべてに、パワーを＋1000し、ソウルを＋1。"
	],
	"specialAttrib": null,
	"version": "4",
	"cardcode": "LB/W02-100",
	"imageURL": "https://ws-tcg.com/wordpress/wp-content/images/l/lb_w02/lb_w02_100.png",
	"tags": null,
	"expansionId": 2
}