{
	"set": "DC",
	"setName": "2013年度トライアルデッキ【W】",
	"side": "W",
	"release": "23",
	"id": "T02",
	"name": "",
	"jpName": "素敵な彼氏と 和泉子",
	"cardType": "CH",
	"colour": "YELLOW",
	"level": "0",
	"cost": "0",
	"power": "2500",
	"soul": "1",
	"rarity": "TD",
	"breakDeckbuilding": false,
	"EN_Equivalent": false,
	"flavourText": "",
	"trigger": [],
	"ability": [
		"【自】 このカードが手札から舞台に置かれた時、あなたは自分の山札の上から1枚を公開する。そのカードがクライマックスなら、あなたは自分のキャラを1枚選び、そのターン中、ソウルを＋2。（公開したカードは元に戻す）"
	],
	"specialAttrib": [
		"宇宙人",
		"シャケ"
	]
}