{
	"set": "Kka",
	"setName": "Key all-star",
	"side": "W",
	"release": "102",
	"id": "016",
	"name": "",
	"jpName": "空気の読めない初代主人公 祐一",
	"cardType": "CH",
	"colour": "YELLOW",
	"level": "0",
	"cost": "0",
	"power": "1500",
	"soul": "1",
	"rarity": "U",
	"breakDeckbuilding": false,
	"EN_Equivalent": false,
	"flavourText": "",
	"trigger": [],
	"ability": [
		"【自】 あなたのクライマックスフェイズの始めに、あなたは自分の、《Anniversary》か《冬》のキャラを1枚選び、そのターン中、パワーを＋500。",
		"【起】 集中 ［(1) このカードを【レスト】する］ あなたは自分の山札の上から4枚をめくり、控え室に置く。それらのカードのクライマックス1枚につき、あなたは自分の控え室のキャラを1枚まで選び、手札に戻す。"
	],
	"specialAttrib": [
		"Anniversary",
		"冬"
	],
	"version": "2",
	"cardcode": "Kka/W102-016"
}