{
	"set": "BD",
	"setName": "「バンドリ！ ガールズバンドパーティ！」Vol.2",
	"side": "W",
	"release": "63",
	"id": "074",
	"name": "",
	"jpName": "“秘密の場所”市ヶ谷有咲",
	"cardType": "CH",
	"colour": "BLUE",
	"level": "0",
	"cost": "0",
	"power": "1000",
	"soul": "1",
	"rarity": "R",
	"breakDeckbuilding": false,
	"EN_Equivalent": false,
	"flavourText": "",
	"trigger": [],
	"ability": [
		"【自】［(1) 手札を1枚控え室に置く］ このカードが手札から舞台に置かれた時、あなたはコストを払ってよい。そうしたら、あなたは自分の山札を上から3枚まで見て、カードを1枚まで選び、手札に加え、残りのカードを控え室に置く。"
	],
	"specialAttrib": [
		"音楽",
		"Poppin'Party"
	],
	"version": "3",
	"cardcode": "BD/W63-074",
	"imageURL": "/wordpress/wp-content/images/cardlist/b/bd_w63/bd_w63_074.png",
	"tags": null
}