{
	"set": "LHS",
	"setName": "ラブライブ！蓮ノ空女学院スクールアイドルクラブ feat. Link！Like！ラブライブ！",
	"side": "W",
	"release": "122",
	"id": "052S",
	"name": "",
	"jpName": "抱きしめる花びら 村野 さやか",
	"cardType": "CH",
	"colour": "RED",
	"level": "2",
	"cost": "1",
	"power": "5000",
	"soul": "1",
	"rarity": "SR",
	"breakDeckbuilding": false,
	"EN_Equivalent": false,
	"flavourText": "",
	"trigger": [
		"SOUL"
	],
	"ability": [
		"【自】 このカードが手札から舞台に置かれた時、あなたは自分のキャラを1枚選び、そのターン中、ソウルを＋1。",
		"【起】［このカードを控え室に置く］ あなたは相手のキャラを1枚選び、手札に戻す。"
	],
	"specialAttrib": [
		"音楽",
		"DOLLCHESTRA"
	],
	"version": "3",
	"cardcode": "LHS/W122-052S",
	"imageURL": "/wordpress/wp-content/images/cardlist/l/lhs_w122/lhs_w122_052s.png",
	"tags": null
}