{
	"set": "BD",
	"setName": "BanG Dream!",
	"side": "W",
	"release": "47",
	"id": "089",
	"name": "",
	"jpName": "“クライブ”たえ",
	"cardType": "CH",
	"colour": "BLUE",
	"level": "1",
	"cost": "0",
	"power": "4500",
	"soul": "1",
	"rarity": "R",
	"breakDeckbuilding": false,
	"EN_Equivalent": false,
	"flavourText": "一口かじればあふれちゃう！―",
	"trigger": null,
	"ability": [
		"【永】 他のあなたの《音楽》のキャラ1枚につき、このカードのパワーを＋500。"
	],
	"specialAttrib": [
		"音楽",
		"うさぎ"
	],
	"version": "4",
	"cardcode": "BD/W47-089",
	"imageURL": "https://ws-tcg.com/wordpress/wp-content/images/b/bd_w47/bd_w47_089.png",
	"tags": null,
	"expansionId": 196
}