{
	"set": "SBY",
	"setName": "青春ブタ野郎はバニーガール先輩の夢を見ない",
	"side": "W",
	"release": "64",
	"id": "056",
	"name": "",
	"jpName": "なすのとお出迎え 梓川 かえで",
	"cardType": "CH",
	"colour": "RED",
	"level": "1",
	"cost": "0",
	"power": "5500",
	"soul": "1",
	"rarity": "R",
	"breakDeckbuilding": false,
	"EN_Equivalent": false,
	"flavourText": "",
	"trigger": [],
	"ability": [
		"【永】 このカードはサイドアタックできない。",
		"【自】【CXコンボ】 このカードのバトル相手が【リバース】した時、あなたのクライマックス置場に「なすのと一緒」があるなら、あなたは自分の控え室のキャラを1枚選び、手札に戻してよい。"
	],
	"specialAttrib": [
		"思春期",
		"動物"
	],
	"version": "2",
	"cardcode": "SBY/W64-056"
}