{
	"set": "MAR",
	"setName": "MARVEL Vol.2",
	"side": "S",
	"release": "113",
	"id": "089",
	"name": "",
	"jpName": "“クリント・バートン”ホークアイ",
	"cardType": "CH",
	"colour": "BLUE",
	"level": "1",
	"cost": "0",
	"power": "3500",
	"soul": "1",
	"rarity": "U",
	"breakDeckbuilding": false,
	"EN_Equivalent": false,
	"flavourText": "",
	"trigger": [],
	"ability": [
		"【自】 このカードが手札から舞台に置かれたターン中、アタックフェイズの始めに、あなたは自分の山札を上から3枚まで見て、山札の上に好きな順番で置く。",
		"【自】［(1) このカードを控え室に置く］ 他のあなたの《MARVEL》のキャラが舞台から控え室に置かれた時、後列にこのカードがいるなら、あなたはコストを払ってよい。そうしたら、そのキャラをそのキャラがいた枠に【レスト】して置き、そのターンの次のターンの終わりまで、パワーを＋3000。"
	],
	"specialAttrib": [
		"MARVEL"
	],
	"version": "3",
	"cardcode": "MAR/S113-089",
	"imageURL": "/wordpress/wp-content/images/cardlist/m/mar_s113/mar_s113_089.png",
	"tags": null
}